CHANGES.txt
CONTRIBUTORS.txt
MANIFEST.in
README.rst
setup.py
lxmlmechanize/__init__.py
lxmlmechanize/core.py
lxmlmechanize/form.py
lxmlmechanize/mime.py
lxmlmechanize/parser.py
lxmlmechanize.egg-info/PKG-INFO
lxmlmechanize.egg-info/SOURCES.txt
lxmlmechanize.egg-info/dependency_links.txt
lxmlmechanize.egg-info/entry_points.txt
lxmlmechanize.egg-info/requires.txt
lxmlmechanize.egg-info/top_level.txt
lxmlmechanize.egg-info/zip-safe
lxmlmechanize/html/__init__.py
lxmlmechanize/html/dtdutil.py
lxmlmechanize/html/tests.py
lxmlmechanize/html/utils.py
lxmlmechanize/urllib2ext/__init__.py
lxmlmechanize/urllib2ext/auth.py
lxmlmechanize/urllib2ext/tests.py