Metadata-Version: 1.1
Name: lxmlmechanize
Version: 0.0.1
Summary: UNKNOWN
Home-page: https://github.com/moriyoshi/lxmlmechanize
Author: Moriyoshi Koizumi
Author-email: mozo@mozo.jp
License: UNKNOWN
Platform: UNKNOWN
Classifier: Topic :: Internet
Classifier: Topic :: Internet :: WWW/HTTP
Classifier: Topic :: Internet :: WWW/HTTP :: Browsers
Classifier: License :: OSI Approved :: BSD License
Classifier: Operating System :: OS Independent
Classifier: Programming Language :: Python
Classifier: Programming Language :: Python :: 2.5
Classifier: Programming Language :: Python :: 2.6
Classifier: Programming Language :: Python :: 2.7
Classifier: Topic :: Software Development :: Libraries
Classifier: Topic :: Software Development :: Libraries :: Python Modules
Classifier: Topic :: Software Development :: Testing
Classifier: Topic :: Software Development :: Testing :: Traffic Generation
